setup.py
brynq_sdk_zermelo/__init__.py
brynq_sdk_zermelo/zermelo.py
brynq_sdk_zermelo.egg-info/PKG-INFO
brynq_sdk_zermelo.egg-info/SOURCES.txt
brynq_sdk_zermelo.egg-info/dependency_links.txt
brynq_sdk_zermelo.egg-info/not-zip-safe
brynq_sdk_zermelo.egg-info/requires.txt
brynq_sdk_zermelo.egg-info/top_level.txt